pymesos/__init__.py
pymesos/detector.py
pymesos/executor.py
pymesos/launcher.py
pymesos/messages_pb2.py
pymesos/process.py
pymesos/scheduler.py
pymesos/zkpython.py
pymesos/subprocess/__init__.py
pymesos/subprocess/executor.py
pymesos/subprocess/popen.py
pymesos/subprocess/scheduler.py
pymesos-0.1.6.dist-info/DESCRIPTION.rst
pymesos-0.1.6.dist-info/METADATA
pymesos-0.1.6.dist-info/RECORD
pymesos-0.1.6.dist-info/WHEEL
pymesos-0.1.6.dist-info/metadata.json
pymesos-0.1.6.dist-info/top_level.txt
