Metadata-Version: 2.0
Name: pymesos
Version: 0.1.6
Summary: A pure python implementation of Mesos scheduler and executor
Home-page: https://github.com/douban/pymesos
Author: Zhongbo Tian
Author-email: tianzhongbo@douban.com
License: UNKNOWN
Download-URL: https://github.com/douban/pymesos/archive/0.1.6.tar.gz
Platform: POSIX
Classifier: Intended Audience :: Developers
Classifier: License :: OSI Approved :: BSD License
Classifier: Operating System :: POSIX
Classifier: Programming Language :: Python
Requires-Dist: mesos.interface (>=0.25)
